<?xml version="1.0" encoding="utf-8"?>
<SoundBanksInfo Platform="Windows" BasePlatform="Windows" SchemaVersion="12" SoundbankVersion="140">
	<RootPaths>
		<ProjectRoot>D:\unity Projects\Hunters-Of-The-High-Road\Assets\Hunters-Of-The-High-Road_WwiseProject\</ProjectRoot>
		<SourceFilesRoot>D:\unity Projects\Hunters-Of-The-High-Road\Assets\Hunters-Of-The-High-Road_WwiseProject\.cache\Windows\</SourceFilesRoot>
		<SoundBanksRoot>D:\unity Projects\Hunters-Of-The-High-Road\Assets\Hunters-Of-The-High-Road_WwiseProject\GeneratedSoundBanks\Windows\</SoundBanksRoot>
		<ExternalSourcesInputFile></ExternalSourcesInputFile>
		<ExternalSourcesOutputRoot>D:\unity Projects\Hunters-Of-The-High-Road\Assets\Hunters-Of-The-High-Road_WwiseProject\GeneratedSoundBanks\Windows</ExternalSourcesOutputRoot>
	</RootPaths>
	<SoundBanks>
		<SoundBank Id="1467963052" Language="SFX" Hash="3186828977">
			<ObjectPath>\SoundBanks\Default Work Unit\Weapons</ObjectPath>
			<ShortName>Weapons</ShortName>
			<Path>Weapons.bnk</Path>
			<IncludedEvents>
				<Event Id="1620154736" Name="Play_Rifle_Blend_Container" ObjectPath="\Events\Default Work Unit\Play_Rifle_Blend_Container">
					<IncludedMemoryFiles>
						<File Id="153752956" Language="SFX">
							<ShortName>sfx_weapon_rifle_reloadclick_01.wav</ShortName>
							<Path>SFX\sfx_weapon_rifle_reloadclick_01_10C4C929.wem</Path>
						</File>
						<File Id="181635655" Language="SFX">
							<ShortName>sfx_weapon_rifle_shoot_04.wav</ShortName>
							<Path>SFX\sfx_weapon_rifle_shoot_04_65E96FB4.wem</Path>
						</File>
						<File Id="352362709" Language="SFX">
							<ShortName>sfx_weapon_rifle_shoot_01.wav</ShortName>
							<Path>SFX\sfx_weapon_rifle_shoot_01_C2101D1F.wem</Path>
						</File>
						<File Id="809742197" Language="SFX">
							<ShortName>sfx_weapon_rifle_trigerpull_01.WAV</ShortName>
							<Path>SFX\sfx_weapon_rifle_trigerpull_01_F92F67CC.wem</Path>
						</File>
						<File Id="818144569" Language="SFX">
							<ShortName>sfx_weapon_rifle_shoot_02.wav</ShortName>
							<Path>SFX\sfx_weapon_rifle_shoot_02_3B1C5ED7.wem</Path>
						</File>
						<File Id="927481850" Language="SFX">
							<ShortName>sfx_weapon_rifle_shoot_03.wav</ShortName>
							<Path>SFX\sfx_weapon_rifle_shoot_03_B126AF28.wem</Path>
						</File>
					</IncludedMemoryFiles>
				</Event>
				<Event Id="2602512053" Name="Play_sward_full" ObjectPath="\Events\Default Work Unit\Play_sward_full">
					<IncludedMemoryFiles>
						<File Id="243304111" Language="SFX">
							<ShortName>sward pull.wav</ShortName>
							<Path>SFX\sward pull_89EBE3D3.wem</Path>
						</File>
						<File Id="282849044" Language="SFX">
							<ShortName>sfx_weapon_sword_metal_01.wav</ShortName>
							<Path>SFX\sfx_weapon_sword_metal_01_10C4C929.wem</Path>
						</File>
						<File Id="284620773" Language="SFX">
							<ShortName>sfx_weapon_sword_metal_03.wav</ShortName>
							<Path>SFX\sfx_weapon_sword_metal_03_10C4C929.wem</Path>
						</File>
						<File Id="342281756" Language="SFX">
							<ShortName>sfx_weapon_sword_slash_01.wav</ShortName>
							<Path>SFX\sfx_weapon_sword_slash_01_10C4C929.wem</Path>
						</File>
						<File Id="356225369" Language="SFX">
							<ShortName>sfx_weapon_sword_slash_02.wav</ShortName>
							<Path>SFX\sfx_weapon_sword_slash_02_10C4C929.wem</Path>
						</File>
						<File Id="547661489" Language="SFX">
							<ShortName>sfx_weapon_sword_metal_02.wav</ShortName>
							<Path>SFX\sfx_weapon_sword_metal_02_10C4C929.wem</Path>
						</File>
						<File Id="658589117" Language="SFX">
							<ShortName>sfx_weapon_sword_blessedmetal_01.wav</ShortName>
							<Path>SFX\sfx_weapon_sword_blessedmetal_01_40300E98.wem</Path>
						</File>
						<File Id="956961059" Language="SFX">
							<ShortName>sfx_weapon_sword_metal_04.wav</ShortName>
							<Path>SFX\sfx_weapon_sword_metal_04_10C4C929.wem</Path>
						</File>
					</IncludedMemoryFiles>
				</Event>
			</IncludedEvents>
		</SoundBank>
	</SoundBanks>
</SoundBanksInfo>
